{
  "_note1": "KEEP THIS FILE! Check it into a version control system (VCS) like git.",
  "_note2": "ObjectBox manages crucial IDs for your object model. See docs for details.",
  "_note3": "If you have VCS merge conflicts, you must resolve them according to ObjectBox docs.",
  "entities": [
    {
      "id": "1:7931200849091418353",
      "lastPropertyId": "4:5917834142320156986",
      "name": "User",
      "properties": [
        {
          "id": "1:2271581505741807848",
          "name": "id"
        },
        {
          "id": "2:760388365394505999",
          "name": "email"
        },
        {
          "id": "3:5928048856084665947",
          "name": "pass"
        },
        {
          "id": "4:5917834142320156986",
          "name": "isActive"
        }
      ],
      "relations": []
    }
  ],
  "lastEntityId": "1:7931200849091418353",
  "lastIndexId": "0:0",
  "lastRelationId": "0:0",
  "lastSequenceId": "0:0",
  "modelVersion": 4,
  "modelVersionParserMinimum": 4,
  "retiredEntityUids": [],
  "retiredIndexUids": [],
  "retiredPropertyUids": [],
  "retiredRelationUids": [],
  "version": 1
}